eola/__init__.py
eola/clients/__init__.py
eola/clients/lambda.py
eola/connection.py
eola/enums/__init__.py
eola/enums/engine.py
eola/executors/__init__.py
eola/planner/__init__.py
eola/planner/plan.py
eola/servers/__init__.py
eola/servers/lambda.py
eola-0.1.0.dist-info/METADATA
eola-0.1.0.dist-info/WHEEL
eola-0.1.0.dist-info/RECORD
