Metadata-Version: 2.1
Name: eola
Version: 0.1.0
Summary: Open Source Distributed DuckDB
License: MIT
Author: cheunhong
Author-email: chlin6755@gmail.com
Requires-Python: >=3.10,<4.0
Classifier: License :: OSI Approved :: MIT License
Classifier: Programming Language :: Python :: 3
Classifier: Programming Language :: Python :: 3.10
Classifier: Programming Language :: Python :: 3.11
Requires-Dist: boto3 (>=1.28.82,<2.0.0)
Requires-Dist: duckdb (>=0.9.1,<0.10.0)
Requires-Dist: numpy (>=1.26.2,<2.0.0)
Requires-Dist: pandas (>=2.1.4,<3.0.0)
Requires-Dist: sqlglot (>=19.8.3,<20.0.0)
